fcmpy/__init__.py
fcmpy/expert_fcm/__init__.py
fcmpy/expert_fcm/aggregation.py
fcmpy/expert_fcm/checkers.py
fcmpy/expert_fcm/defuzz.py
fcmpy/expert_fcm/entropy.py
fcmpy/expert_fcm/expert_based_fcm.py
fcmpy/expert_fcm/implication.py
fcmpy/expert_fcm/input_validator.py
fcmpy/expert_fcm/membership.py
fcmpy/expert_fcm/reader.py
fcmpy/expert_fcm/transform.py
fcmpy/intervention/__init__.py
fcmpy/intervention/intervention.py
fcmpy/intervention/interventionConstructor.py
fcmpy/ml/__init__.py
fcmpy/ml/validation.py
fcmpy/ml/classification/FCM_MP.py
fcmpy/ml/classification/__init__.py
fcmpy/ml/classification/eltcn.py
fcmpy/ml/genetic/__init__.py
fcmpy/ml/genetic/auxiliary.py
fcmpy/ml/genetic/evaluation.py
fcmpy/ml/genetic/fitness.py
fcmpy/ml/genetic/ga_interface.py
fcmpy/ml/genetic/generational_ga.py
fcmpy/ml/genetic/initialization.py
fcmpy/ml/genetic/matrix_error.py
fcmpy/ml/genetic/mutation.py
fcmpy/ml/genetic/normalization.py
fcmpy/ml/genetic/rcga.py
fcmpy/ml/genetic/recombination.py
fcmpy/ml/genetic/replacement.py
fcmpy/ml/genetic/selection.py
fcmpy/ml/genetic/ssga.py
fcmpy/ml/hebbian/__init__.py
fcmpy/ml/hebbian/ahl.py
fcmpy/ml/hebbian/nhl.py
fcmpy/ml/hebbian/termination.py
fcmpy/ml/hebbian/update_parameters.py
fcmpy/ml/hebbian/update_state.py
fcmpy/ml/hebbian/update_weight.py
fcmpy/simulator/__init__.py
fcmpy/simulator/convergence.py
fcmpy/simulator/inference.py
fcmpy/simulator/simulator.py
fcmpy/simulator/transfer.py
fcmpy/store/__init__.py
fcmpy/store/methodsStore.py
unittests/__init__.py
unittests/test_Intervention.py
unittests/test_expertFcm.py
unittests/test_rcga.py
unittests/test_simulator.py
fcmpy-0.0.21.dist-info/LICENSE.txt
fcmpy-0.0.21.dist-info/METADATA
fcmpy-0.0.21.dist-info/WHEEL
fcmpy-0.0.21.dist-info/top_level.txt
fcmpy-0.0.21.dist-info/RECORD
