Metadata-Version: 2.1
Name: fcmpy
Version: 0.0.21
Summary: Fuzzy Cognitive Maps for Behavior Change Interventions and Evaluation
Home-page: https://github.com/SamvelMK/FcmBci.git
Author: Samvel Mkhitaryan, Philippe J. Giabbanelli, Maciej Wozniak, Nanne K. de Vries, Rik Crutzen
Author-email: mkhitarian.samvel@gmail.com
License: UNKNOWN
Platform: UNKNOWN
Classifier: Programming Language :: Python :: 3
Classifier: License :: OSI Approved :: MIT License
Classifier: Operating System :: OS Independent
Requires-Python: >=3.8.1
License-File: LICENSE.txt
Requires-Dist: numpy (>=1.13.3)
Requires-Dist: pandas (==1.3.3)
Requires-Dist: tqdm (==4.62.3)
Requires-Dist: matplotlib (==3.4.3)
Requires-Dist: scipy (==1.7.1)
Requires-Dist: scikit-learn (==0.24.2)
Requires-Dist: tensorflow (>=2.6.0)
Requires-Dist: pillow (==8.4.0)
Requires-Dist: cycler (==0.11.0)
Requires-Dist: kiwisolver (==1.3.2)
Requires-Dist: pytz (==2021.3)
Requires-Dist: joblib (==1.1.0)
Requires-Dist: absl-py (>=0.10)
Requires-Dist: gast (>=0.4.0)
Requires-Dist: astunparse (==1.6.3)
Requires-Dist: keras-preprocessing (==1.1.2)
Requires-Dist: flatbuffers (>=1.12.0)
Requires-Dist: seaborn (==0.11.2)
Requires-Dist: scikit-fuzzy (>=0.4.2)
Requires-Dist: openpyxl
Requires-Dist: xlrd (==1.2.0)
Requires-Dist: python-dateutil
Requires-Dist: google
Requires-Dist: google-api-python-client
Requires-Dist: opt-einsum
